.gitignore
.svnignore
CHANGES.txt
CONTRIBUTORS.txt
MANIFEST.in
README.txt
setup.cfg
setup.py
Products/__init__.py
Products.OSHATranslations.egg-info/PKG-INFO
Products.OSHATranslations.egg-info/SOURCES.txt
Products.OSHATranslations.egg-info/dependency_links.txt
Products.OSHATranslations.egg-info/entry_points.txt
Products.OSHATranslations.egg-info/namespace_packages.txt
Products.OSHATranslations.egg-info/not-zip-safe
Products.OSHATranslations.egg-info/requires.txt
Products.OSHATranslations.egg-info/top_level.txt
Products/OSHATranslations/README.txt
Products/OSHATranslations/__init__.py
Products/OSHATranslations/i18n/osha-bg.po
Products/OSHATranslations/i18n/osha-cs.po
Products/OSHATranslations/i18n/osha-da.po
Products/OSHATranslations/i18n/osha-de.po
Products/OSHATranslations/i18n/osha-el.po
Products/OSHATranslations/i18n/osha-en.po
Products/OSHATranslations/i18n/osha-es.po
Products/OSHATranslations/i18n/osha-et.po
Products/OSHATranslations/i18n/osha-fi.po
Products/OSHATranslations/i18n/osha-fr.po
Products/OSHATranslations/i18n/osha-hr.po
Products/OSHATranslations/i18n/osha-hu.po
Products/OSHATranslations/i18n/osha-hwi-bg.po
Products/OSHATranslations/i18n/osha-hwi-cs.po
Products/OSHATranslations/i18n/osha-hwi-el.po
Products/OSHATranslations/i18n/osha-hwi-en.po
Products/OSHATranslations/i18n/osha-hwi-et.po
Products/OSHATranslations/i18n/osha-hwi-hu.po
Products/OSHATranslations/i18n/osha-hwi-lt.po
Products/OSHATranslations/i18n/osha-hwi-lv.po
Products/OSHATranslations/i18n/osha-hwi-mt.po
Products/OSHATranslations/i18n/osha-hwi-pl.po
Products/OSHATranslations/i18n/osha-hwi-ro.po
Products/OSHATranslations/i18n/osha-hwi-sk.po
Products/OSHATranslations/i18n/osha-hwi-sl.po
Products/OSHATranslations/i18n/osha-is.po
Products/OSHATranslations/i18n/osha-it.po
Products/OSHATranslations/i18n/osha-ja.po
Products/OSHATranslations/i18n/osha-lt.po
Products/OSHATranslations/i18n/osha-lv.po
Products/OSHATranslations/i18n/osha-mt.po
Products/OSHATranslations/i18n/osha-napo.bg.po
Products/OSHATranslations/i18n/osha-napo.cs.po
Products/OSHATranslations/i18n/osha-napo.da.po
Products/OSHATranslations/i18n/osha-napo.de.po
Products/OSHATranslations/i18n/osha-napo.el.po
Products/OSHATranslations/i18n/osha-napo.en.po
Products/OSHATranslations/i18n/osha-napo.es.po
Products/OSHATranslations/i18n/osha-napo.et.po
Products/OSHATranslations/i18n/osha-napo.fi.po
