Metadata-Version: 1.0
Name: Products.OSHATranslations
Version: 1.2.38
Summary: Translations for the osha project
Home-page: https://svn.syslab.com/svn/OSHA/Products.OSHATranslations
Author: Syslab.com GmbH
Author-email: mailto:info@syslab.com
License: GPL + EUPL
Keywords: osha translations
Platform: UNKNOWN
Classifier: Framework :: Plone
Classifier: Intended Audience :: Developers
Classifier: Topic :: Software Development :: Libraries :: Python Modules
Classifier: License :: OSI Approved :: GNU General Public License (GPL)
Classifier: License :: OSI Approved :: European Union Public Licence 1.1 (EUPL 1.1)
